COPYING
MANIFEST.in
README.md
setup.py
prof/__init__.py
prof/config.py
prof/main.py
prof/make.py
prof/session.py
prof/tools.py
prof/version.py
prof/work.py
prof.egg-info/PKG-INFO
prof.egg-info/SOURCES.txt
prof.egg-info/dependency_links.txt
prof.egg-info/entry_points.txt
prof.egg-info/requires.txt
prof.egg-info/top_level.txt
prof/parsers/__init__.py
prof/parsers/field_html_parser.py
prof/parsers/work_html_parser.py