Metadata-Version: 1.1
Name: prof
Version: 1.1.0
Summary: A tool to upload student work to http://prof.fil.univ-lille1.fr
Home-page: http://github.com/calve/prof
Author: calve
Author-email: calvinh34@gmail.com
License: UNKNOWN
Platform: UNKNOWN
Classifier: Programming Language :: Python
Classifier: Programming Language :: Python :: 3
Classifier: License :: Public Domain
Classifier: Operating System :: OS Independent
Classifier: Environment :: Console
